cdktf_cdktf_provider_dns/__init__.py
cdktf_cdktf_provider_dns/py.typed
cdktf_cdktf_provider_dns/_jsii/__init__.py
cdktf_cdktf_provider_dns/_jsii/provider-dns@9.0.0.jsii.tgz
cdktf_cdktf_provider_dns/a_record_set/__init__.py
cdktf_cdktf_provider_dns/aaaa_record_set/__init__.py
cdktf_cdktf_provider_dns/cname_record/__init__.py
cdktf_cdktf_provider_dns/data_dns_a_record_set/__init__.py
cdktf_cdktf_provider_dns/data_dns_aaaa_record_set/__init__.py
cdktf_cdktf_provider_dns/data_dns_cname_record_set/__init__.py
cdktf_cdktf_provider_dns/data_dns_mx_record_set/__init__.py
cdktf_cdktf_provider_dns/data_dns_ns_record_set/__init__.py
cdktf_cdktf_provider_dns/data_dns_ptr_record_set/__init__.py
cdktf_cdktf_provider_dns/data_dns_srv_record_set/__init__.py
cdktf_cdktf_provider_dns/data_dns_txt_record_set/__init__.py
cdktf_cdktf_provider_dns/mx_record_set/__init__.py
cdktf_cdktf_provider_dns/ns_record_set/__init__.py
cdktf_cdktf_provider_dns/provider/__init__.py
cdktf_cdktf_provider_dns/ptr_record/__init__.py
cdktf_cdktf_provider_dns/srv_record_set/__init__.py
cdktf_cdktf_provider_dns/txt_record_set/__init__.py
cdktf_cdktf_provider_dns-9.0.0.dist-info/LICENSE
cdktf_cdktf_provider_dns-9.0.0.dist-info/METADATA
cdktf_cdktf_provider_dns-9.0.0.dist-info/WHEEL
cdktf_cdktf_provider_dns-9.0.0.dist-info/top_level.txt
cdktf_cdktf_provider_dns-9.0.0.dist-info/RECORD
